ZixiPay/__init__.py
ZixiPay/api.py
ZixiPay/utils.py
ZixiPay/types/__init__.py
ZixiPay/types/balance.py
ZixiPay/types/exchange.py
ZixiPay/types/fee.py
ZixiPay/types/invoice.py
ZixiPay/types/rate.py
ZixiPay/types/transaction.py
ZixiPay/types/wallet.py
ZixiPay-0.0.1.dist-info/LICENSE
ZixiPay-0.0.1.dist-info/METADATA
ZixiPay-0.0.1.dist-info/WHEEL
ZixiPay-0.0.1.dist-info/top_level.txt
ZixiPay-0.0.1.dist-info/RECORD
