Metadata-Version: 2.1
Name: ZixiPay
Version: 0.0.1
Summary: An asynchronous ZixiPay API wrapper
Author-email: lyteloli <me@lyteloli.space>
License: GNU GENERAL PUBLIC LICENSE
Project-URL: Homepage, https://github.com/lyteloli/ZixiPay
Project-URL: Bug Tracker, https://github.com/lyteloli/ZixiPay/issues
Classifier: Programming Language :: Python :: 3
Classifier: License :: OSI Approved :: GNU General Public License (GPL)
Classifier: Operating System :: OS Independent
Classifier: Framework :: aiohttp
Classifier: Intended Audience :: Developers
Classifier: Topic :: Software Development
Requires-Python: >=3.7
License-File: LICENSE
Requires-Dist: aiohttp
